FormatFusion/__init__.py
FormatFusion/converter.py
FormatFusion/io.py
formatfusion-0.2.6.dist-info/METADATA
formatfusion-0.2.6.dist-info/WHEEL
formatfusion-0.2.6.dist-info/licenses/AUTHORS.txt
formatfusion-0.2.6.dist-info/licenses/LICENSE
formatfusion-0.2.6.dist-info/RECORD
