Metadata-Version: 2.3
Name: FormatFusion
Version: 0.2.6
Summary: Effortlessly Convert Between Data Formats with FormatFusion. FormatFusion is your one-stop solution for seamless conversion between YAML, JSON, XML, and CSV formats.
Project-URL: Homepage, https://github.com/aliftech/FormatFusion
Project-URL: Bug Tracker, https://github.com/aliftech/FormatFusion/issues
Author-email: Wahyu Krisna Aji <wahyukrisnaaji32@gmail.com>
License-File: AUTHORS.txt
License-File: LICENSE
Classifier: License :: OSI Approved :: MIT License
Classifier: Operating System :: OS Independent
Classifier: Programming Language :: Python :: 3
Requires-Python: >=3.8
